odoo/addons/sale_commission_geo_assign_product_domain/README.rst
odoo/addons/sale_commission_geo_assign_product_domain/__init__.py
odoo/addons/sale_commission_geo_assign_product_domain/__manifest__.py
odoo/addons/sale_commission_geo_assign_product_domain/i18n/es.po
odoo/addons/sale_commission_geo_assign_product_domain/i18n/it.po
odoo/addons/sale_commission_geo_assign_product_domain/i18n/sale_commission_geo_assign_product_domain.pot
odoo/addons/sale_commission_geo_assign_product_domain/models/__init__.py
odoo/addons/sale_commission_geo_assign_product_domain/models/res_partner.py
odoo/addons/sale_commission_geo_assign_product_domain/models/res_partner_commission_group.py
odoo/addons/sale_commission_geo_assign_product_domain/readme/CONFIGURE.rst
odoo/addons/sale_commission_geo_assign_product_domain/readme/CONTRIBUTORS.rst
odoo/addons/sale_commission_geo_assign_product_domain/readme/DESCRIPTION.rst
odoo/addons/sale_commission_geo_assign_product_domain/readme/USAGE.rst
odoo/addons/sale_commission_geo_assign_product_domain/security/ir.model.access.csv
odoo/addons/sale_commission_geo_assign_product_domain/static/description/icon.png
odoo/addons/sale_commission_geo_assign_product_domain/static/description/index.html
odoo/addons/sale_commission_geo_assign_product_domain/tests/__init__.py
odoo/addons/sale_commission_geo_assign_product_domain/tests/test_sale_commission_geo_assign_product_domain.py
odoo/addons/sale_commission_geo_assign_product_domain/views/res_partner_commission_group_view.xml
odoo/addons/sale_commission_geo_assign_product_domain/views/res_partner_view.xml
odoo/addons/sale_commission_geo_assign_product_domain/wizards/__init__.py
odoo/addons/sale_commission_geo_assign_product_domain/wizards/wizard_geo_assign_partner.py
odoo14_addon_sale_commission_geo_assign_product_domain-14.0.1.3.2.dist-info/METADATA
odoo14_addon_sale_commission_geo_assign_product_domain-14.0.1.3.2.dist-info/WHEEL
odoo14_addon_sale_commission_geo_assign_product_domain-14.0.1.3.2.dist-info/top_level.txt
odoo14_addon_sale_commission_geo_assign_product_domain-14.0.1.3.2.dist-info/RECORD
