Metadata-Version: 2.1
Name: odoo14-addon-sale_commission_geo_assign_product_domain
Version: 14.0.1.3.2
Summary: Bridge module between sale_commission_product_criteria_domain and sale_commission_geo_assign
Home-page: https://github.com/OCA/commission
Author: PyTech SRL, Ooops404, Odoo Community Association (OCA)
Author-email: support@odoo-community.org
License: AGPL-3
Classifier: Programming Language :: Python
Classifier: Framework :: Odoo
Classifier: Framework :: Odoo :: 14.0
Classifier: License :: OSI Approved :: GNU Affero General Public License v3
Requires-Python: >=3.6
Requires-Dist: odoo14-addon-sale-commission-geo-assign
Requires-Dist: odoo14-addon-sale-commission-product-criteria-domain
Requires-Dist: odoo <14.1dev,>=14.0a
